acampreq/__init__.py
acampreq/req.py
acampreq-2.2.dist-info/LICENSE.txt
acampreq-2.2.dist-info/METADATA
acampreq-2.2.dist-info/WHEEL
acampreq-2.2.dist-info/top_level.txt
acampreq-2.2.dist-info/RECORD
