Metadata-Version: 2.1
Name: acampreq
Version: 2.2
Summary: 给A营用户的post项目
Home-page: https://pypi.org
Author: I_am_back
Author-email: 2682786816@qq.com
License: UNKNOWN
Platform: UNKNOWN
Classifier: Programming Language :: Python :: 3.8
Classifier: License :: OSI Approved :: MIT License
Classifier: Operating System :: OS Independent
Classifier: Natural Language :: Chinese (Simplified)
Classifier: Development Status :: 5 - Production/Stable
Requires-Dist: req-iab (>=1.3)
